{
  "$id": "http://example.com/example.json",
  "type": "object",
  "definitions": {},
  "$schema": "http://json-schema.org/draft-07/schema#",
  "properties": {
    "CleaningAndDisinfectionProducts": {
      "$id": "/properties/CleaningAndDisinfectionProducts",
      "type": "object",
      "properties": {
        "D1": {
          "$id": "/properties/CleaningAndDisinfectionProducts/properties/D1",
          "type": "object",
          "properties": {
            "cdProceduresSwitch": {
              "$id": "/properties/CleaningAndDisinfectionProducts/properties/D1/properties/cdProceduresSwitch",
              "type": "boolean",
              "title": "The Cdproceduresswitch Schema ",
              "default": false,
              "examples": [
                true
              ],
              "if": { "cdProceduresSwitch": true },
              "then": {
                "required": [ "cdProceduresSwitch" ]
              }
            }
          },
          "cdProceduresComments": {
            "$id": "/properties/CleaningAndDisinfectionProducts/properties/D1/properties/cdProceduresComments",
            "type": "string",
            "title": "The Cdprocedurescomments Schema ",
            "default": "",
            "examples": [
              "default comments"
            ],
            "if": { "cdProceduresComments": { "string": "1" } },
            "then": {
              "required": [ "cdProceduresSwitch" ]
            }
          }
        }
      }
    }

  }
}